cp1/__init__.py
cp1/core.py
cp1/cp1am.py
cp1/interactive/__init__.py
cp1/interactive/cp1teractive.py
cp1/io/__init__.py
cp1/io/cp1iogrib.py
iamiki_cp1-2024.11.0.dist-info/LICENSE
iamiki_cp1-2024.11.0.dist-info/METADATA
iamiki_cp1-2024.11.0.dist-info/WHEEL
iamiki_cp1-2024.11.0.dist-info/top_level.txt
iamiki_cp1-2024.11.0.dist-info/RECORD
