Metadata-Version: 2.1
Name: iamiki_cp1
Version: 2024.11.0
Summary: M-Profiles for marine evaporation ducts.
Author-email: IAMiki <miki4ia@gmail.com>
License: BSD-3-Clause
Keywords: meteo,marine,duct,evaporation,lmo,Monin-Obukhov
Classifier: Programming Language :: Python :: 3
Classifier: Operating System :: OS Independent
Classifier: Natural Language :: English
Classifier: Topic :: Scientific/Engineering
Classifier: Topic :: Scientific/Engineering :: Atmospheric Science
Classifier: Intended Audience :: Science/Research
Requires-Python: >=3.8
License-File: LICENSE
Requires-Dist: pandas
Requires-Dist: numpy
Requires-Dist: matplotlib
Provides-Extra: grib
Requires-Dist: cfgrib; extra == "grib"
Requires-Dist: eccodes; extra == "grib"
Provides-Extra: interactive
Requires-Dist: plotly; extra == "interactive"
Requires-Dist: IPython; extra == "interactive"
